Metadata-Version: 2.1
Name: httpx
Version: 0.21.3
Summary: The next generation HTTP client.
Home-page: https://github.com/encode/httpx
Author: Tom Christie
Author-email: tom@tomchristie.com
License: BSD
Project-URL: Changelog, https://github.com/encode/httpx/blob/master/CHANGELOG.md
Project-URL: Documentation, https://www.python-httpx.org
Project-URL: Source, https://github.com/encode/httpx
Platform: UNKNOWN
Classifier: Development Status :: 4 - Beta
Classifier: Environment :: Web Environment
Classifier: Intended Audience :: Developers
Classifier: License :: OSI Approved :: BSD License
Classifier: Operating System :: OS Independent
Classifier: Topic :: Internet :: WWW/HTTP
Classifier: Framework :: AsyncIO
Classifier: Framework :: Trio
Classifier: Programming Language :: Python :: 3
Classifier: Programming Language :: Python :: 3.6
Classifier: Programming Language :: Python :: 3.7
Classifier: Programming Language :: Python :: 3.8
Classifier: Programming Language :: Python :: 3.9
Classifier: Programming Language :: Python :: 3.10
Classifier: Programming Language :: Python :: 3 :: Only
Requires-Python: >=3.6
Provides-Extra: http2
Provides-Extra: brotli
Provides-Extra: cli
